pyerector/__init__.py
pyerector/api.py
pyerector/args.py
pyerector/base.py
pyerector/config.py
pyerector/exception.py
pyerector/execute.py
pyerector/helper.py
pyerector/iterators.py
pyerector/main.py
pyerector/metaclass.py
pyerector/path.py
pyerector/register.py
pyerector/targets.py
pyerector/unit-test.py
pyerector/variables.py
pyerector/version.py
pyerector/py2/__init__.py
pyerector/py2/base.py
pyerector/py3/__init__.py
pyerector/py3/base.py
pyerector/py3/execfile.py
pyerector/tasks/__init__.py
pyerector/tasks/_base.py
pyerector/tasks/_container.py
pyerector/tasks/chmod.py
pyerector/tasks/copy.py
pyerector/tasks/copytree.py
pyerector/tasks/download.py
pyerector/tasks/echo.py
pyerector/tasks/egg.py
pyerector/tasks/encodevar.py
pyerector/tasks/hashgen.py
pyerector/tasks/java.py
pyerector/tasks/mkdir.py
pyerector/tasks/pip_module.py
pyerector/tasks/pycompile.py
pyerector/tasks/remove.py
pyerector/tasks/shebang.py
pyerector/tasks/spawn.py
pyerector/tasks/sshengine.py
pyerector/tasks/subpyerector.py
pyerector/tasks/symlink.py
pyerector/tasks/tar.py
pyerector/tasks/tokenize.py
pyerector/tasks/touch.py
pyerector/tasks/unittest.py
pyerector/tasks/untar.py
pyerector/tasks/unzip.py
pyerector/tasks/zip.py
pyerector/vcs/__init__.py
pyerector/vcs/base.py
pyerector/vcs/git.py
pyerector/vcs/mercurial.py
pyerector/vcs/none.py
pyerector/vcs/subversion.py
pyerector-1.3.1.1.dist-info/DESCRIPTION.rst
pyerector-1.3.1.1.dist-info/METADATA
pyerector-1.3.1.1.dist-info/RECORD
pyerector-1.3.1.1.dist-info/WHEEL
pyerector-1.3.1.1.dist-info/metadata.json
pyerector-1.3.1.1.dist-info/top_level.txt
