Metadata-Version: 2.0
Name: pyerector
Version: 1.3.1.1
Summary: Self-contained Python build library
Home-page: http://bitbucket.org/Arcege/pyerector
Author: Michael P. Reilly
Author-email: arcege@gmail.com
License: License :: OSI Approved :: GNU General Public License v3 (GPLv3)
Download-URL: http://pypi.python.org/pypi/pyerector
Platform: UNKNOWN
Classifier: Development Status :: 4 - Beta
Classifier: Environment :: Console
Classifier: Intended Audience :: Developers
Classifier: Operating System :: MacOS :: MacOS X
Classifier: Operating System :: Microsoft
Classifier: Operating System :: POSIX
Classifier: Programming Language :: Python :: 2.6
Classifier: Programming Language :: Python :: 2.7
Classifier: Programming Language :: Python :: 3
Classifier: Topic :: Software Development :: Build Tools
